ticketeer_linux/__init__.py
ticketeer_linux-0.1.5.dist-info/METADATA
ticketeer_linux-0.1.5.dist-info/WHEEL
ticketeer_linux-0.1.5.dist-info/top_level.txt
ticketeer_linux-0.1.5.dist-info/RECORD
