Metadata-Version: 2.1
Name: ticketeer_linux
Version: 0.1.5
Summary: The Linux binaries for ticketeer, commit message utility.
Author-email: Mikhael Khrustik <misha@myrt.co>
License: MIT
Keywords: git,hook
Classifier: License :: OSI Approved :: MIT License
Classifier: Development Status :: 5 - Production/Stable
Classifier: Intended Audience :: Developers
Classifier: Programming Language :: Python :: 3.9
Classifier: Programming Language :: Python :: 3.10
Classifier: Programming Language :: Python :: 3.11
Classifier: Programming Language :: Python :: 3.12
Classifier: Programming Language :: Python :: 3.13
Classifier: Operating System :: POSIX :: Linux
Requires-Python: >=3.9
